aind_metadata_mapper/__init__.py
aind_metadata_mapper/core.py
aind_metadata_mapper/core_models.py
aind_metadata_mapper/gather_metadata.py
aind_metadata_mapper/models.py
aind_metadata_mapper/bergamo/__init__.py
aind_metadata_mapper/bergamo/models.py
aind_metadata_mapper/bergamo/session.py
aind_metadata_mapper/bruker/__init__.py
aind_metadata_mapper/bruker/models.py
aind_metadata_mapper/bruker/session.py
aind_metadata_mapper/dynamic_routing/__init__.py
aind_metadata_mapper/dynamic_routing/mvr_rig.py
aind_metadata_mapper/dynamic_routing/neuropixels_rig.py
aind_metadata_mapper/dynamic_routing/sync_rig.py
aind_metadata_mapper/dynamic_routing/utils.py
aind_metadata_mapper/exaspim/__init__.py
aind_metadata_mapper/fip/__init__.py
aind_metadata_mapper/fip/example_create_session.py
aind_metadata_mapper/fip/models.py
aind_metadata_mapper/fip/session.py
aind_metadata_mapper/fip/utils.py
aind_metadata_mapper/isi/__init__.py
aind_metadata_mapper/isi/models.py
aind_metadata_mapper/isi/session.py
aind_metadata_mapper/mesoscope/__init__.py
aind_metadata_mapper/mesoscope/data_description.py
aind_metadata_mapper/mesoscope/models.py
aind_metadata_mapper/mesoscope/session.py
aind_metadata_mapper/open_ephys/__init__.py
aind_metadata_mapper/open_ephys/camstim_ephys_session.py
aind_metadata_mapper/open_ephys/models.py
aind_metadata_mapper/open_ephys/rig.py
aind_metadata_mapper/open_ephys/session.py
aind_metadata_mapper/open_ephys/utils/behavior_utils.py
aind_metadata_mapper/open_ephys/utils/constants.py
aind_metadata_mapper/open_ephys/utils/naming_utils.py
aind_metadata_mapper/open_ephys/utils/pkl_utils.py
aind_metadata_mapper/open_ephys/utils/stim_utils.py
aind_metadata_mapper/open_ephys/utils/sync_utils.py
aind_metadata_mapper/opto_fiber_benchmark/__init__.py
aind_metadata_mapper/opto_fiber_benchmark/models.py
aind_metadata_mapper/opto_fiber_benchmark/session.py
aind_metadata_mapper/pavlovian_behavior/__init__.py
aind_metadata_mapper/pavlovian_behavior/example_create_session.py
aind_metadata_mapper-0.29.3.dist-info/licenses/LICENSE
aind_metadata_mapper-0.29.3.dist-info/METADATA
aind_metadata_mapper-0.29.3.dist-info/WHEEL
aind_metadata_mapper-0.29.3.dist-info/top_level.txt
aind_metadata_mapper-0.29.3.dist-info/RECORD
